fresh_baked_skeleton/__init__.py
fresh_baked_skeleton/cli.py
fresh_baked_skeleton/main.py
fresh_baked_skeleton-0.1.0a124.dist-info/entry_points.txt
fresh_baked_skeleton-0.1.0a124.dist-info/LICENSE
fresh_baked_skeleton-0.1.0a124.dist-info/WHEEL
fresh_baked_skeleton-0.1.0a124.dist-info/METADATA
fresh_baked_skeleton-0.1.0a124.dist-info/RECORD
