Metadata-Version: 2.1
Name: fresh-baked-skeleton
Version: 0.1.0a124
Summary: Short Description of My Library
Home-page: https://github.com/Curly-Mo/fresh-baked-skeleton
License: LGPL-3.0
Author: Colin Fahy
Author-email: colin@cfahy.com
Requires-Python: >=3.6,<4.0
Classifier: License :: OSI Approved :: GNU Lesser General Public License v3 (LGPLv3)
Classifier: Programming Language :: Python
Classifier: Programming Language :: Python :: 3
Classifier: Programming Language :: Python :: 3.6
Classifier: Programming Language :: Python :: 3.7
Provides-Extra: mypy
Requires-Dist: click (>=6.7,<7.0)
Requires-Dist: typing (>=3.6,<4.0)
Project-URL: Documentation, https://fresh_baked_skeleton.readthedocs.org/en/latest/
Project-URL: Repository, https://github.com/Curly-Mo/fresh-baked-skeleton
